osm_integration_haystack/__init__.py
osm_integration_haystack/osm_doc_converter.py
osm_integration_haystack/osm_fetcher.py
osm_integration_haystack/overpass_client.py
osm_integration_haystack/utils/geo_utils.py
osm_integration_haystack-0.1.11.dist-info/licenses/LICENSE
osm_integration_haystack-0.1.11.dist-info/METADATA
osm_integration_haystack-0.1.11.dist-info/WHEEL
osm_integration_haystack-0.1.11.dist-info/top_level.txt
osm_integration_haystack-0.1.11.dist-info/RECORD
