Metadata-Version: 2.4
Name: osm-integration-haystack
Version: 0.1.11
Summary: A Haystack component integrating Overpass API for OpenStreetMap
Author-email: "Wyatt \"Huaye\" Wei" <h.w_wyatt@protonmail.com>
License: MIT
Project-URL: Homepage, https://github.com/grexrr/osm-integration-haystack
Classifier: License :: OSI Approved :: MIT License
Classifier: Programming Language :: Python :: 3
Classifier: Programming Language :: Python :: 3.11
Classifier: Programming Language :: Python :: 3.12
Classifier: Operating System :: OS Independent
Requires-Python: >=3.11
License-File: LICENSE
Requires-Dist: haystack-ai>=2.0.0
Requires-Dist: requests>=2.25.0
Dynamic: license-file
